lobar/__init__.py
lobar/cli.py
lobar/lobar.py
lobar-0.1.0.dist-info/DESCRIPTION.rst
lobar-0.1.0.dist-info/METADATA
lobar-0.1.0.dist-info/RECORD
lobar-0.1.0.dist-info/WHEEL
lobar-0.1.0.dist-info/entry_points.txt
lobar-0.1.0.dist-info/metadata.json
lobar-0.1.0.dist-info/top_level.txt
