Metadata-Version: 2.0
Name: lobar
Version: 0.1.0
Summary: A python utility library
Home-page: https://github.com/mhetrerajat/lobar
Author: Rajat Mhetre
Author-email: mhetrerajat@gmail.com
License: MIT license
Keywords: lobar
Platform: UNKNOWN
Classifier: Development Status :: 2 - Pre-Alpha
Classifier: Intended Audience :: Developers
Classifier: License :: OSI Approved :: MIT License
Classifier: Natural Language :: English
Classifier: Programming Language :: Python :: 2
Classifier: Programming Language :: Python :: 2.6
Classifier: Programming Language :: Python :: 2.7
Classifier: Programming Language :: Python :: 3
Classifier: Programming Language :: Python :: 3.3
Classifier: Programming Language :: Python :: 3.4
Classifier: Programming Language :: Python :: 3.5
Requires-Dist: Click (>=6.0)
